django_upload_path/__init__.py
django_upload_path/upload_path.py
django_upload_path-0.1.1.dist-info/DESCRIPTION.rst
django_upload_path-0.1.1.dist-info/METADATA
django_upload_path-0.1.1.dist-info/RECORD
django_upload_path-0.1.1.dist-info/WHEEL
django_upload_path-0.1.1.dist-info/metadata.json
django_upload_path-0.1.1.dist-info/top_level.txt
django_upload_path-0.1.1.dist-info/zip-safe
