Metadata-Version: 2.0
Name: django-upload-path
Version: 0.1.1
Summary: Various implementations for the Django ``FileField/ImageField.upload_to`` model field attribute.
Home-page: https://github.com/illagrenan/django-upload-path
Author: Vasek Dohnal
Author-email: vaclav.dohnal@gmail.com
License: MIT
Platform: UNKNOWN
Classifier: Development Status :: 3 - Alpha
Classifier: Framework :: Django
Classifier: Framework :: Django :: 1.8
Classifier: Framework :: Django :: 1.10
Classifier: Framework :: Django :: 1.11
Classifier: Intended Audience :: Developers
Classifier: License :: OSI Approved :: MIT License
Classifier: Natural Language :: English
Classifier: Programming Language :: Python :: 3.4
Classifier: Programming Language :: Python :: 3.5
Classifier: Programming Language :: Python :: 3.6
Classifier: Programming Language :: Python :: 3 :: Only
Classifier: Operating System :: OS Independent
Classifier: Programming Language :: Python :: Implementation :: CPython
Classifier: Programming Language :: Python :: Implementation :: PyPy
Requires-Python: ~=3.4
Requires-Dist: django
Requires-Dist: typing; python_version<'3.5'
